MANIFEST.in
README.md
setup.py
fabrik_cli/__init__.py
fabrik_cli/generator.py
fabrik_cli/utils.py
fabrik_cli.egg-info/PKG-INFO
fabrik_cli.egg-info/SOURCES.txt
fabrik_cli.egg-info/dependency_links.txt
fabrik_cli.egg-info/entry_points.txt
fabrik_cli.egg-info/not-zip-safe
fabrik_cli.egg-info/requires.txt
fabrik_cli.egg-info/top_level.txt
fabrik_cli/scripts/__init__.py
fabrik_cli/scripts/cleanup.py
fabrik_cli/scripts/init.py
fabrik_cli/templates/fabfile.py.txt
fabrik_cli/templates/fabricrc.txt
fabrik_cli/templates/index.py.txt
fabrik_cli/templates/stage.py.txt
requirements/dev.txt
requirements/install.txt
requirements/tests.txt