Metadata-Version: 1.0
Name: fabrik-cli
Version: 2.0.0
Summary: CLI tool for scaffolding fabrik files 
Home-page: https://github.com/frojd/fabrik-cli
Author: Fröjd
Author-email: martin.sandstrom@frojd.se
License: MIT
Platform: UNKNOWN
